bycolors/__config__.py
bycolors/__init__.py
bycolors/by_palette.py
bycolors/cmap.py
bycolors/color_class.py
bycolors/palette.py
bycolors/utils.py
bycolors/tests/__init__.py
bycolors/tests/test_base_palette.py
bycolors/tests/test_by_palette.py
bycolors/tests/test_color_class.py
bycolors-0.4.1.dist-info/METADATA
bycolors-0.4.1.dist-info/WHEEL
bycolors-0.4.1.dist-info/top_level.txt
bycolors-0.4.1.dist-info/RECORD
