Metadata-Version: 2.1
Name: bycolors
Version: 0.4.1
Summary: Blue and yellow colors for matplotlib.
Home-page: https://github.com/kyrylo-gr/b-y-colors
Author: kyrylo.gr
Author-email: git@kyrylo.gr
Classifier: Programming Language :: Python :: 3
Classifier: Operating System :: OS Independent
Requires-Python: >=3.7
